karrio/mappers/canpar/__init__.py
karrio/mappers/canpar/mapper.py
karrio/mappers/canpar/proxy.py
karrio/mappers/canpar/settings.py
karrio/plugins/canpar/__init__.py
karrio/providers/canpar/__init__.py
karrio/providers/canpar/address.py
karrio/providers/canpar/error.py
karrio/providers/canpar/rate.py
karrio/providers/canpar/tracking.py
karrio/providers/canpar/units.py
karrio/providers/canpar/utils.py
karrio/providers/canpar/pickup/__init__.py
karrio/providers/canpar/pickup/cancel.py
karrio/providers/canpar/pickup/create.py
karrio/providers/canpar/pickup/update.py
karrio/providers/canpar/shipment/__init__.py
karrio/providers/canpar/shipment/cancel.py
karrio/providers/canpar/shipment/create.py
karrio/providers/canpar/shipment/label.py
karrio/schemas/canpar/CanparAddonsService.py
karrio/schemas/canpar/CanparRatingService.py
karrio/schemas/canpar/CanshipBusinessService.py
karrio/schemas/canpar/__init__.py
karrio_canpar-2026.1.4.dist-info/METADATA
karrio_canpar-2026.1.4.dist-info/WHEEL
karrio_canpar-2026.1.4.dist-info/entry_points.txt
karrio_canpar-2026.1.4.dist-info/top_level.txt
karrio_canpar-2026.1.4.dist-info/RECORD
